butt/__init__.py
butt-0.1.dist-info/METADATA
butt-0.1.dist-info/RECORD
butt-0.1.dist-info/WHEEL
butt-0.1.dist-info/top_level.txt
