Metadata-Version: 2.1
Name: butt
Version: 0.1
Summary: A command line client for scuttlebutt.
Home-page: https://github.com/supakeen/butt
Author: supakeen
Author-email: cmdr@supakeen.com
License: UNKNOWN
Platform: UNKNOWN
Requires-Dist: scuttlebutt
